mawo_pymorphy3/__init__.py
mawo_pymorphy3/dawg_dictionary.py
mawo_pymorphy3/dawg_optimizer.py
mawo_pymorphy3/py.typed
mawo_pymorphy3/dicts_ru/grammemes.json
mawo_pymorphy3/dicts_ru/gramtab-opencorpora-ext.json
mawo_pymorphy3/dicts_ru/gramtab-opencorpora-int.json
mawo_pymorphy3/dicts_ru/meta.json
mawo_pymorphy3/dicts_ru/paradigms.array
mawo_pymorphy3/dicts_ru/prediction-suffixes-0.dawg
mawo_pymorphy3/dicts_ru/prediction-suffixes-1.dawg
mawo_pymorphy3/dicts_ru/prediction-suffixes-2.dawg
mawo_pymorphy3/dicts_ru/suffixes.json
mawo_pymorphy3/dicts_ru/words.dawg
mawo_pymorphy3-1.0.4.dist-info/licenses/LICENSE
tests/test_comprehensive.py
tests/test_dawg.py
tests/test_integration.py
tests/pymorphy2_compat/conftest.py
tests/pymorphy2_compat/shapes_utils.py
tests/pymorphy2_compat/test_inflection.py
tests/pymorphy2_compat/test_parsing.py
mawo_pymorphy3-1.0.4.dist-info/METADATA
mawo_pymorphy3-1.0.4.dist-info/WHEEL
mawo_pymorphy3-1.0.4.dist-info/top_level.txt
mawo_pymorphy3-1.0.4.dist-info/RECORD
