Metadata-Version: 2.4
Name: mawo-pymorphy3
Version: 1.0.4
Summary: Улучшенный морфологический анализатор для русского языка с DAWG-оптимизацией и сокращением памяти на 90%
Author-email: MAWO Team <team@mawo.ru>
Maintainer-email: MAWO Team <team@mawo.ru>
License: MIT
Project-URL: Homepage, https://github.com/mawo-ru/mawo-pymorphy3
Project-URL: Documentation, https://github.com/mawo-ru/mawo-pymorphy3#readme
Project-URL: Repository, https://github.com/mawo-ru/mawo-pymorphy3
Project-URL: Issues, https://github.com/mawo-ru/mawo-pymorphy3/issues
Project-URL: Changelog, https://github.com/mawo-ru/mawo-pymorphy3/blob/main/CHANGELOG.md
Keywords: nlp,russian,morphology,pymorphy3,dawg,mawo
Classifier: Development Status :: 5 - Production/Stable
Classifier: Intended Audience :: Developers
Classifier: Intended Audience :: Science/Research
Classifier: License :: OSI Approved :: MIT License
Classifier: Natural Language :: Russian
Classifier: Operating System :: OS Independent
Classifier: Programming Language :: Python :: 3
Classifier: Programming Language :: Python :: 3.9
Classifier: Programming Language :: Python :: 3.10
Classifier: Programming Language :: Python :: 3.11
Classifier: Programming Language :: Python :: 3.12
Classifier: Programming Language :: Python :: 3.13
Classifier: Topic :: Scientific/Engineering :: Artificial Intelligence
Classifier: Topic :: Text Processing :: Linguistic
Requires-Python: >=3.9
License-File: LICENSE
Requires-Dist: dawg-python>=0.7.2
Requires-Dist: tqdm>=4.66.0
Provides-Extra: dev
Requires-Dist: pytest>=7.0; extra == "dev"
Requires-Dist: black>=23.0; extra == "dev"
Requires-Dist: ruff>=0.1.0; extra == "dev"
Requires-Dist: mypy>=1.0; extra == "dev"
Provides-Extra: security
Requires-Dist: defusedxml>=0.7.1; extra == "security"
Provides-Extra: rich
Requires-Dist: rich>=13.0; extra == "rich"
Provides-Extra: all
Requires-Dist: mawo-pymorphy3[dev,rich,security]; extra == "all"
Dynamic: license-file
